Paquetes/Paquete.py
Paquete.py-1.0.dist-info/METADATA
Paquete.py-1.0.dist-info/WHEEL
Paquete.py-1.0.dist-info/top_level.txt
Paquete.py-1.0.dist-info/RECORD
