Metadata-Version: 2.1
Name: Paquete.py
Version: 1.0
Summary: A useful module
Author: DaniQB
